polyaxon_k8s/__init__.py
polyaxon_k8s/constants.py
polyaxon_k8s/exceptions.py
polyaxon_k8s/logger.py
polyaxon_k8s/manager.py
tests/__init__.py
tests/base.py
tests/test_manager.py
polyaxon_k8s-0.5.0.dist-info/LICENSE
polyaxon_k8s-0.5.0.dist-info/METADATA
polyaxon_k8s-0.5.0.dist-info/WHEEL
polyaxon_k8s-0.5.0.dist-info/top_level.txt
polyaxon_k8s-0.5.0.dist-info/RECORD
