Metadata-Version: 2.1
Name: polyaxon-k8s
Version: 0.5.0
Summary: Polyaxon Kubernetes managers, utils, and resources.
Home-page: https://github.com/polyaxon/polyaxon-k8s
Author: Mourad Mourafiq
Author-email: mourad@polyaxon.com
Maintainer: Mourad Mourafiq
Maintainer-email: mourad@polyaxon.com
License: MIT
Keywords: polyaxon,tensorFlow,deep-learning,machine-learning,data-science,neural-networks,artificial-intelligence,ai,reinforcement-learning,kubernetes
Platform: any
Classifier: Programming Language :: Python
Classifier: Operating System :: OS Independent
Classifier: Intended Audience :: Developers
Classifier: Intended Audience :: Science/Research
Classifier: Topic :: Scientific/Engineering :: Artificial Intelligence
Requires-Dist: kubernetes (==10.0.1)
Requires-Dist: PyYAML (>=5.1)
Requires-Dist: six (>=1.12.0)
